AUTHORS.rst
CONTRIBUTING.rst
HISTORY.rst
MANIFEST.in
README.rst
setup.cfg
setup.py
docs/Makefile
docs/authors.rst
docs/conf.py
docs/contributing.rst
docs/history.rst
docs/index.rst
docs/installation.rst
docs/make.bat
docs/readme.rst
docs/usage.rst
tests/__init__.py
tests/test_usertrue.py
usertrue/__init__.py
usertrue/cli.py
usertrue/usertrue.py
usertrue.egg-info/PKG-INFO
usertrue.egg-info/SOURCES.txt
usertrue.egg-info/dependency_links.txt
usertrue.egg-info/entry_points.txt
usertrue.egg-info/not-zip-safe
usertrue.egg-info/requires.txt
usertrue.egg-info/top_level.txt